whatprovides/__init__.py
whatprovides/tests.py
whatprovides/version.py
whatprovides/whatprovides.py
whatprovides-1.4.dist-info/LICENSE.txt
whatprovides-1.4.dist-info/METADATA
whatprovides-1.4.dist-info/WHEEL
whatprovides-1.4.dist-info/entry_points.txt
whatprovides-1.4.dist-info/top_level.txt
whatprovides-1.4.dist-info/RECORD
