Metadata-Version: 2.1
Name: whatprovides
Version: 1.4
Summary: UNKNOWN
Home-page: https://github.com/shmakovpn/whatprovides
Author: shmakovpn
Author-email: shmakovpn@yandex.ru
License: UNKNOWN
Download-URL: https://github.com/shmakovpn/whatprovides/archive/1.4.zip
Platform: UNKNOWN
Classifier: Programming Language :: Python :: 3
Classifier: Environment :: Console
Classifier: License :: OSI Approved :: Apache Software License
Classifier: Operating System :: OS Independent
Requires-Python: >=3.6
Requires-Dist: chardet
